pybotforge/__init__.py
pybotforge/client.py
pybotforge/commands.py
pybotforge/events.py
pybotforge/utils.py
pybotforge-0.1.0.dist-info/METADATA
pybotforge-0.1.0.dist-info/WHEEL
pybotforge-0.1.0.dist-info/top_level.txt
pybotforge-0.1.0.dist-info/RECORD
