Metadata-Version: 2.1
Name: pybotforge
Version: 0.1.0
Summary: A simplified framework for creating Discord bots in Python.
Author: Your Name
Classifier: Programming Language :: Python :: 3
Classifier: License :: OSI Approved :: MIT License
Classifier: Operating System :: OS Independent
Requires-Python: >=3.8
Requires-Dist: discord.py
